semantic_clustify/__init__.py
semantic_clustify/algorithms.py
semantic_clustify/cli.py
semantic_clustify/core.py
semantic_clustify/utils.py
semantic_clustify-1.2.0.dist-info/licenses/LICENSE
semantic_clustify-1.2.0.dist-info/METADATA
semantic_clustify-1.2.0.dist-info/WHEEL
semantic_clustify-1.2.0.dist-info/entry_points.txt
semantic_clustify-1.2.0.dist-info/top_level.txt
semantic_clustify-1.2.0.dist-info/RECORD
