Metadata-Version: 2.4
Name: semantic-clustify
Version: 1.2.0
Summary: A powerful and flexible Python tool for semantic clustering of text documents using vector embeddings
Home-page: https://github.com/changyy/py-semantic-clustify
Author: changyy
Author-email: changyy <changyy.csie@gmail.com>
License-Expression: MIT
Project-URL: Homepage, https://github.com/changyy/py-semantic-clustify
Project-URL: Repository, https://github.com/changyy/py-semantic-clustify
Project-URL: Issues, https://github.com/changyy/py-semantic-clustify/issues
Classifier: Development Status :: 4 - Beta
Classifier: Intended Audience :: Developers
Classifier: Intended Audience :: Science/Research
Classifier: Operating System :: OS Independent
Classifier: Programming Language :: Python :: 3
Classifier: Programming Language :: Python :: 3.8
Classifier: Programming Language :: Python :: 3.9
Classifier: Programming Language :: Python :: 3.10
Classifier: Programming Language :: Python :: 3.11
Classifier: Programming Language :: Python :: 3.12
Classifier: Topic :: Scientific/Engineering :: Artificial Intelligence
Classifier: Topic :: Scientific/Engineering :: Information Analysis
Classifier: Topic :: Text Processing
Requires-Python: >=3.8
License-File: LICENSE
Requires-Dist: numpy>=1.21.0
Requires-Dist: scikit-learn>=1.0.0
Requires-Dist: click>=8.0.0
Requires-Dist: tqdm>=4.60.0
Provides-Extra: faiss
Requires-Dist: faiss-cpu>=1.7.0; extra == "faiss"
Provides-Extra: advanced
Requires-Dist: scipy>=1.7.0; extra == "advanced"
Requires-Dist: matplotlib>=3.5.0; extra == "advanced"
Requires-Dist: seaborn>=0.11.0; extra == "advanced"
Provides-Extra: visualization
Requires-Dist: matplotlib>=3.5.0; extra == "visualization"
Requires-Dist: seaborn>=0.11.0; extra == "visualization"
Requires-Dist: plotly>=5.0.0; extra == "visualization"
Provides-Extra: all
Requires-Dist: faiss-cpu>=1.7.0; extra == "all"
Requires-Dist: scipy>=1.7.0; extra == "all"
Requires-Dist: matplotlib>=3.5.0; extra == "all"
Requires-Dist: seaborn>=0.11.0; extra == "all"
Requires-Dist: plotly>=5.0.0; extra == "all"
Provides-Extra: dev
Requires-Dist: pytest>=7.0.0; extra == "dev"
Requires-Dist: pytest-cov>=4.0.0; extra == "dev"
Requires-Dist: black>=22.0.0; extra == "dev"
Requires-Dist: flake8>=5.0.0; extra == "dev"
Requires-Dist: mypy>=1.0.0; extra == "dev"
Requires-Dist: build>=0.8.0; extra == "dev"
Requires-Dist: twine>=4.0.0; extra == "dev"
Dynamic: author
Dynamic: home-page
Dynamic: license-file
Dynamic: requires-python
